adafruit_circuitpython_rfm-1.0.10.dist-info/licenses/LICENSE
adafruit_rfm/__init__.py
adafruit_rfm/rfm69.py
adafruit_rfm/rfm9x.py
adafruit_rfm/rfm9xfsk.py
adafruit_rfm/rfm_common.py
adafruit_circuitpython_rfm-1.0.10.dist-info/METADATA
adafruit_circuitpython_rfm-1.0.10.dist-info/WHEEL
adafruit_circuitpython_rfm-1.0.10.dist-info/top_level.txt
adafruit_circuitpython_rfm-1.0.10.dist-info/RECORD
