Metadata-Version: 2.4
Name: adafruit-circuitpython-rfm
Version: 1.0.10
Summary: Support for RFM69 and RFM9x modules
Author-email: Adafruit Industries <circuitpython@adafruit.com>
License: MIT
Project-URL: Homepage, https://github.com/jerryneedell/Adafruit_CircuitPython_RFM
Keywords: adafruit,blinka,circuitpython,micropython,rfm,RFM69,RFM9x,radio
Classifier: Intended Audience :: Developers
Classifier: Topic :: Software Development :: Libraries
Classifier: Topic :: Software Development :: Embedded Systems
Classifier: Topic :: System :: Hardware
Classifier: License :: OSI Approved :: MIT License
Classifier: Programming Language :: Python :: 3
License-File: LICENSE
Requires-Dist: Adafruit-Blinka
Requires-Dist: adafruit-circuitpython-busdevice
Requires-Dist: asyncio
Provides-Extra: optional
Dynamic: license-file
